reactivex/__init__.py
reactivex/_version.py
reactivex/abc/__init__.py
reactivex/abc/disposable.py
reactivex/abc/observable.py
reactivex/abc/observer.py
reactivex/abc/periodicscheduler.py
reactivex/abc/scheduler.py
reactivex/abc/startable.py
reactivex/abc/subject.py
reactivex/disposable/__init__.py
reactivex/disposable/booleandisposable.py
reactivex/disposable/compositedisposable.py
reactivex/disposable/disposable.py
reactivex/disposable/multipleassignmentdisposable.py
reactivex/disposable/refcountdisposable.py
reactivex/disposable/scheduleddisposable.py
reactivex/disposable/serialdisposable.py
reactivex/disposable/singleassignmentdisposable.py
reactivex/internal/__init__.py
reactivex/internal/basic.py
reactivex/internal/concurrency.py
reactivex/internal/constants.py
reactivex/internal/exceptions.py
reactivex/internal/priorityqueue.py
reactivex/internal/utils.py
reactivex/notification.py
reactivex/observable/__init__.py
reactivex/observable/amb.py
reactivex/observable/case.py
reactivex/observable/catch.py
reactivex/observable/combinelatest.py
reactivex/observable/concat.py
reactivex/observable/connectableobservable.py
reactivex/observable/defer.py
reactivex/observable/empty.py
reactivex/observable/forkjoin.py
reactivex/observable/fromcallback.py
reactivex/observable/fromfuture.py
reactivex/observable/fromiterable.py
reactivex/observable/generate.py
reactivex/observable/generatewithrelativetime.py
reactivex/observable/groupedobservable.py
reactivex/observable/ifthen.py
reactivex/observable/interval.py
reactivex/observable/marbles.py
reactivex/observable/merge.py
reactivex/observable/never.py
reactivex/observable/observable.py
reactivex/observable/onerrorresumenext.py
reactivex/observable/range.py
reactivex/observable/repeat.py
reactivex/observable/returnvalue.py
reactivex/observable/start.py
reactivex/observable/startasync.py
reactivex/observable/throw.py
reactivex/observable/timer.py
reactivex/observable/toasync.py
reactivex/observable/using.py
reactivex-4.0.3.dist-info/LICENSE
reactivex-4.0.3.dist-info/WHEEL
reactivex-4.0.3.dist-info/METADATA
reactivex-4.0.3.dist-info/RECORD
