Metadata-Version: 2.1
Name: reactivex
Version: 4.0.3
Summary: ReactiveX (Rx) for Python
Home-page: http://reactivex.io
License: MIT
Author: Dag Brattli
Author-email: dag@brattli.net
Requires-Python: >=3.7,<3.11
Classifier: Development Status :: 5 - Production/Stable
Classifier: Environment :: Other Environment
Classifier: Intended Audience :: Developers
Classifier: License :: OSI Approved :: MIT License
Classifier: Operating System :: OS Independent
Classifier: Programming Language :: Python :: 3
Classifier: Programming Language :: Python :: 3.10
Classifier: Programming Language :: Python :: 3.7
Classifier: Programming Language :: Python :: 3.8
Classifier: Programming Language :: Python :: 3.9
Classifier: Programming Language :: Python :: Implementation :: CPython
Classifier: Topic :: Software Development :: Libraries :: Python Modules
Requires-Dist: typing-extensions (>=4.1.1,<5.0.0)
Project-URL: Documentation, https://rxpy.readthedocs.io/en/latest/
Project-URL: Repository, https://github.com/ReactiveX/RxPY
